iloko_cli/__init__.py
iloko_cli/cli.py
iloko_cli/interpreter.py
iloko_cli/lexer.py
iloko_cli/parser.py
iloko_cli-1.5.1.dist-info/METADATA
iloko_cli-1.5.1.dist-info/WHEEL
iloko_cli-1.5.1.dist-info/entry_points.txt
iloko_cli-1.5.1.dist-info/top_level.txt
iloko_cli-1.5.1.dist-info/RECORD
