Metadata-Version: 2.4
Name: iloko-cli
Version: 1.5.1
Summary: A command-line interpreter for the ILOKO esolang.
Author: Christian Andrei
Classifier: Programming Language :: Python :: 3
Classifier: License :: OSI Approved :: MIT License
Classifier: Operating System :: OS Independent
Requires-Python: >=3.6
Dynamic: author
Dynamic: classifier
Dynamic: description
Dynamic: description-content-type
Dynamic: requires-python
Dynamic: summary
